hydromt_sfincs/__init__.py
hydromt_sfincs/plots.py
hydromt_sfincs/quadtree.py
hydromt_sfincs/regulargrid.py
hydromt_sfincs/sfincs.py
hydromt_sfincs/sfincs_input.py
hydromt_sfincs/subgrid.py
hydromt_sfincs/utils.py
hydromt_sfincs/data/lulc/NLCD_HSG.csv
hydromt_sfincs/data/lulc/NLCD_SFBD_mapping.csv
hydromt_sfincs/data/lulc/README
hydromt_sfincs/data/lulc/corine_mapping.csv
hydromt_sfincs/data/lulc/esa_worldcover_HSG.csv
hydromt_sfincs/data/lulc/esa_worldcover_mapping.csv
hydromt_sfincs/data/lulc/globcover_mapping.csv
hydromt_sfincs/data/lulc/vito_mapping.csv
hydromt_sfincs/data/sfincs/sfincs.inp
hydromt_sfincs/workflows/__init__.py
hydromt_sfincs/workflows/bathymetry.py
hydromt_sfincs/workflows/curvenumber.py
hydromt_sfincs/workflows/discharge.py
hydromt_sfincs/workflows/downscaling.py
hydromt_sfincs/workflows/flwdir.py
hydromt_sfincs/workflows/landuse.py
hydromt_sfincs/workflows/merge.py
hydromt_sfincs/workflows/storage_volume.py
hydromt_sfincs/workflows/tiling.py
hydromt_sfincs-1.2.1.dist-info/entry_points.txt
hydromt_sfincs-1.2.1.dist-info/licenses/LICENSE
hydromt_sfincs-1.2.1.dist-info/WHEEL
hydromt_sfincs-1.2.1.dist-info/METADATA
hydromt_sfincs-1.2.1.dist-info/RECORD
