Metadata-Version: 2.4
Name: hydromt_sfincs
Version: 1.2.1
Summary: hydroMT plugin for sfincs models.
Author-email: Roel de Goede <roel.degoede@deltares.nl>, Maarten van Ormondt <Maarten.vanOrmondt@deltares-usa.us>, Dirk Eilander <dirk.eilander@deltares.nl>, Tim Leijnse <tim.leijnse@deltares.nl>
Requires-Python: >=3.9
Classifier: Development Status :: 4 - Beta
Classifier: Intended Audience :: Developers
Classifier: Intended Audience :: Science/Research
Classifier: Topic :: Scientific/Engineering :: Hydrology
Classifier: License :: OSI Approved :: GNU General Public License v3 (GPLv3)
Classifier: Programming Language :: Python :: 3
License-File: LICENSE
Requires-Dist: affine
Requires-Dist: geopandas>1.0
Requires-Dist: hydromt>=0.10.1,<1.0
Requires-Dist: numba
Requires-Dist: numpy
Requires-Dist: pandas
Requires-Dist: pillow
Requires-Dist: pyflwdir>=0.5.10
Requires-Dist: pyproj
Requires-Dist: rasterio
Requires-Dist: scipy
Requires-Dist: shapely
Requires-Dist: xarray
Requires-Dist: xugrid>=0.14, <1.0
Requires-Dist: nbsphinx ; extra == "doc"
Requires-Dist: pydata-sphinx-theme ; extra == "doc"
Requires-Dist: sphinx ; extra == "doc"
Requires-Dist: sphinx_design ; extra == "doc"
Requires-Dist: cartopy ; extra == "examples"
Requires-Dist: descartes ; extra == "examples"
Requires-Dist: ffmpeg ; extra == "examples"
Requires-Dist: jupyterlab ; extra == "examples"
Requires-Dist: matplotlib ; extra == "examples"
Requires-Dist: pillow ; extra == "examples"
Requires-Dist: hydromt_sfincs[test, doc, examples] ; extra == "full"
Requires-Dist: datashader ; extra == "quadtree"
Requires-Dist: mapbox_earcut ; extra == "quadtree"
Requires-Dist: black[jupyter] ; extra == "test"
Requires-Dist: pytest>=2.7.3 ; extra == "test"
Requires-Dist: pytest-cov ; extra == "test"
Requires-Dist: pre-commit ; extra == "test"
Project-URL: Documentation, https://deltares.github.io/hydromt_sfincs/
Project-URL: Source, https://github.com/Deltares/hydromt_sfincs
Provides-Extra: doc
Provides-Extra: examples
Provides-Extra: full
Provides-Extra: quadtree
Provides-Extra: test
